odoo9_addon_account_fiscal_position_rule_sale-9.0.1.0.0.99.dev12-py2.7-nspkg.pth
odoo9_addon_account_fiscal_position_rule_sale-9.0.1.0.0.99.dev12.dist-info/METADATA
odoo9_addon_account_fiscal_position_rule_sale-9.0.1.0.0.99.dev12.dist-info/RECORD
odoo9_addon_account_fiscal_position_rule_sale-9.0.1.0.0.99.dev12.dist-info/WHEEL
odoo9_addon_account_fiscal_position_rule_sale-9.0.1.0.0.99.dev12.dist-info/namespace_packages.txt
odoo9_addon_account_fiscal_position_rule_sale-9.0.1.0.0.99.dev12.dist-info/top_level.txt
odoo_addons/account_fiscal_position_rule_sale/README.rst
odoo_addons/account_fiscal_position_rule_sale/__init__.py
odoo_addons/account_fiscal_position_rule_sale/__openerp__.py
odoo_addons/account_fiscal_position_rule_sale/i18n/account_fiscal_position_rule_sale.pot
odoo_addons/account_fiscal_position_rule_sale/i18n/ca.po
odoo_addons/account_fiscal_position_rule_sale/i18n/de.po
odoo_addons/account_fiscal_position_rule_sale/i18n/el_GR.po
odoo_addons/account_fiscal_position_rule_sale/i18n/en_US.po
odoo_addons/account_fiscal_position_rule_sale/i18n/es.po
odoo_addons/account_fiscal_position_rule_sale/i18n/es_ES.po
odoo_addons/account_fiscal_position_rule_sale/i18n/es_VE.po
odoo_addons/account_fiscal_position_rule_sale/i18n/fi.po
odoo_addons/account_fiscal_position_rule_sale/i18n/fr.po
odoo_addons/account_fiscal_position_rule_sale/i18n/hr.po
odoo_addons/account_fiscal_position_rule_sale/i18n/hr_HR.po
odoo_addons/account_fiscal_position_rule_sale/i18n/hu.po
odoo_addons/account_fiscal_position_rule_sale/i18n/it.po
odoo_addons/account_fiscal_position_rule_sale/i18n/nl.po
odoo_addons/account_fiscal_position_rule_sale/i18n/nl_NL.po
odoo_addons/account_fiscal_position_rule_sale/i18n/pt.po
odoo_addons/account_fiscal_position_rule_sale/i18n/pt_BR.po
odoo_addons/account_fiscal_position_rule_sale/i18n/ro.po
odoo_addons/account_fiscal_position_rule_sale/i18n/sk.po
odoo_addons/account_fiscal_position_rule_sale/i18n/sl.po
odoo_addons/account_fiscal_position_rule_sale/i18n/tr.po
odoo_addons/account_fiscal_position_rule_sale/i18n/tr_TR.po
odoo_addons/account_fiscal_position_rule_sale/i18n/vi_VN.po
odoo_addons/account_fiscal_position_rule_sale/i18n/zh_CN.po
odoo_addons/account_fiscal_position_rule_sale/models/__init__.py
odoo_addons/account_fiscal_position_rule_sale/models/sale.py
odoo_addons/account_fiscal_position_rule_sale/security/ir.model.access.csv
